ybc_echarts/__init__.py
ybc_echarts/_version.py
ybc_echarts/base.py
ybc_echarts/chart.py
ybc_echarts/conf.py
ybc_echarts/constants.py
ybc_echarts/engine.py
ybc_echarts/exceptions.py
ybc_echarts/js_extensions.py
ybc_echarts/charts/__init__.py
ybc_echarts/charts/bar.py
ybc_echarts/charts/bar3D.py
ybc_echarts/charts/boxplot.py
ybc_echarts/charts/effectscatter.py
ybc_echarts/charts/funnel.py
ybc_echarts/charts/gauge.py
ybc_echarts/charts/geo.py
ybc_echarts/charts/geolines.py
ybc_echarts/charts/graph.py
ybc_echarts/charts/heatmap.py
ybc_echarts/charts/kline.py
ybc_echarts/charts/line.py
ybc_echarts/charts/line3D.py
ybc_echarts/charts/liquid.py
ybc_echarts/charts/map.py
ybc_echarts/charts/parallel.py
ybc_echarts/charts/pie.py
ybc_echarts/charts/polar.py
ybc_echarts/charts/radar.py
ybc_echarts/charts/sankey.py
ybc_echarts/charts/scatter.py
ybc_echarts/charts/scatter3D.py
ybc_echarts/charts/themeriver.py
ybc_echarts/charts/tree.py
ybc_echarts/charts/treemap.py
ybc_echarts/charts/wordcloud.py
ybc_echarts/custom/__init__.py
ybc_echarts/custom/grid.py
ybc_echarts/custom/overlap.py
ybc_echarts/custom/page.py
ybc_echarts/custom/timeline.py
ybc_echarts/datasets/__init__.py
ybc_echarts/datasets/coordinates.py
ybc_echarts/echarts/__init__.py
ybc_echarts/echarts/axis.py
ybc_echarts/echarts/events.py
ybc_echarts/echarts/json_serializable.py
ybc_echarts/echarts/label.py
ybc_echarts/echarts/line.py
ybc_echarts/echarts/option.py
ybc_echarts/echarts/style.py
ybc_echarts/echarts/tooltip.py
ybc_echarts/utils/__init__.py
ybc_echarts-0.5.8.dist-info/DESCRIPTION.rst
ybc_echarts-0.5.8.dist-info/METADATA
ybc_echarts-0.5.8.dist-info/RECORD
ybc_echarts-0.5.8.dist-info/WHEEL
ybc_echarts-0.5.8.dist-info/metadata.json
ybc_echarts-0.5.8.dist-info/top_level.txt
